qwebtip/__init__.py
qwebtip/cache.py
qwebtip/element_selector.py
qwebtip/qweburltip.py
qwebtip-0.1.0.dist-info/AUTHORS.rst
qwebtip-0.1.0.dist-info/LICENSE
qwebtip-0.1.0.dist-info/METADATA
qwebtip-0.1.0.dist-info/WHEEL
qwebtip-0.1.0.dist-info/top_level.txt
qwebtip-0.1.0.dist-info/RECORD
